{
    "Featured_Items": [
        {
            "iID": "c2dc77e6921cfb8171dddc8441eeb710",
            "iName": "Global: Encryption",
            "iType": "Black Market Decal",
            "iColor": "Purple",
            "iCertification": null,
            "iEdition": null,
            "iPrice": "2200",
            "iUpvote": "1412",
            "iDownvote": "2900",
            "pulltimeCode": 1631784752453,
            "pulltimeText": "16-09-2021 11:32:32"
        },
        {
            "iID": "23751808507ca432fc113cc580f9b321",
            "iName": "Glitch",
            "iType": "Import Wheels",
            "iColor": "Purple",
            "iCertification": null,
            "iEdition": "Glitched",
            "iPrice": "600",
            "iUpvote": "865",
            "iDownvote": "2988",
            "pulltimeCode": 1631784752455,
            "pulltimeText": "16-09-2021 11:32:32"
        }
    ],
    "DailyItems": [
        {
            "iID": "39b34d01259f922ecce791480ecaafab",
            "iName": "Apparatus",
            "iType": "Import Wheels",
            "iColor": "Pink",
            "iCertification": "Acrobat",
            "iEdition": null,
            "iPrice": "600",
            "iUpvote": "87",
            "iDownvote": "1665",
            "pulltimeCode": 1631784752457,
            "pulltimeText": "16-09-2021 11:32:32"
        },
        {
            "iID": "c14c2a888a883df220cc7bc2adede3a2",
            "iName": "Octane: Buzz Kill",
            "iType": "Rare Decal",
            "iColor": "Forest Green",
            "iCertification": null,
            "iEdition": null,
            "iPrice": "100",
            "iUpvote": "116",
            "iDownvote": "1604",
            "pulltimeCode": 1631784752458,
            "pulltimeText": "16-09-2021 11:32:32"
        },
        {
            "iID": "1f6ed252170e2a8489f2e646df95aa88",
            "iName": "Reactor",
            "iType": "Exotic Wheels",
            "iColor": "Saffron",
            "iCertification": null,
            "iEdition": null,
            "iPrice": "900",
            "iUpvote": "328",
            "iDownvote": "1450",
            "pulltimeCode": 1631784752460,
            "pulltimeText": "16-09-2021 11:32:32"
        },
        {
            "iID": "7e22dbf6a2c09763a538e85696df1a52",
            "iName": "Breakout: Taniwha",
            "iType": "Rare Decal",
            "iColor": "Forest Green",
            "iCertification": null,
            "iEdition": null,
            "iPrice": "100",
            "iUpvote": "49",
            "iDownvote": "1633",
            "pulltimeCode": 1631784752461,
            "pulltimeText": "16-09-2021 11:32:32"
        },
        {
            "iID": "16a7852dc1069fde7e347099a92bf2de",
            "iName": "Luminous",
            "iType": "Very Rare Trail",
            "iColor": "Cobalt",
            "iCertification": null,
            "iEdition": null,
            "iPrice": "400",
            "iUpvote": "447",
            "iDownvote": "1343",
            "pulltimeCode": 1631784752463,
            "pulltimeText": "16-09-2021 11:32:32"
        },
        {
            "iID": "b6fd6bc8141cba31ac2677c8549e93f1",
            "iName": "Pulse Crawler",
            "iType": "Very Rare Banner",
            "iColor": "Burnt Sienna",
            "iCertification": null,
            "iEdition": null,
            "iPrice": "200",
            "iUpvote": "91",
            "iDownvote": "1608",
            "pulltimeCode": 1631784752465,
            "pulltimeText": "16-09-2021 11:32:32"
        }
    ]
}