{"Featured_Items":[{"iID":"c4e0c65eb5ce853856316dd59a999fe0","iName":"Gravity Bomb","iType":"Black Market Goal Explosion","iColor":"Forest Green","iCertification":null,"iEdition":null,"iPrice":"2200","iUpvote":"1031","iDownvote":"3615","pulltimeCode":1627934610984,"pulltimeText":"02-08-2021 22:03:30"},{"iID":"ba90c1f7b5ff81ab4a1950595498abd2","iName":"Glaive","iType":"Very Rare Wheels","iColor":"Burnt Sienna","iCertification":"Guardian","iEdition":"Inverted","iPrice":"400","iUpvote":"221","iDownvote":"3993","pulltimeCode":1627934610989,"pulltimeText":"02-08-2021 22:03:30"}],"DailyItems":[{"iID":"1c78f5bc6a1017aeb7342ab8cf5bc019","iName":"Octane: Buzz Kill","iType":"Rare Decal","iColor":"Burnt Sienna","iCertification":null,"iEdition":null,"iPrice":"50","iUpvote":"59","iDownvote":"1099","pulltimeCode":1627934610993,"pulltimeText":"02-08-2021 22:03:30"},{"iID":"5c94ce3ac2d55426a5670eedab5d74a5","iName":"Hexphase","iType":"Very Rare Rocket Boost","iColor":"Titanium White","iCertification":null,"iEdition":null,"iPrice":"400","iUpvote":"827","iDownvote":"505","pulltimeCode":1627934610997,"pulltimeText":"02-08-2021 22:03:30"},{"iID":"bc0a8f06e218f6b9f21ed0c24d70eb7e","iName":"Gaiden","iType":"Very Rare Wheels","iColor":"","iCertification":null,"iEdition":null,"iPrice":"200","iUpvote":"140","iDownvote":"1014","pulltimeCode":1627934611000,"pulltimeText":"02-08-2021 22:03:31"},{"iID":"d148daa92936f8bf84285e03a4f325ab","iName":"Octane: Royal Tyrant","iType":"Rare Decal","iColor":"Black","iCertification":null,"iEdition":null,"iPrice":"100","iUpvote":"284","iDownvote":"849","pulltimeCode":1627934611003,"pulltimeText":"02-08-2021 22:03:31"},{"iID":"76eedc8f0f9a91a05145555e4bced4b2","iName":"X-Devil Mk2","iType":"Import Body","iColor":"Saffron","iCertification":null,"iEdition":null,"iPrice":"800","iUpvote":"44","iDownvote":"1054","pulltimeCode":1627934611005,"pulltimeText":"02-08-2021 22:03:31"},{"iID":"0f5173b36acd1327c4b332361b89f35a","iName":"IO: Infinite","iType":"Import Wheels","iColor":"Forest Green","iCertification":"Acrobat","iEdition":null,"iPrice":"900","iUpvote":"60","iDownvote":"1003","pulltimeCode":1627934611007,"pulltimeText":"02-08-2021 22:03:31"}]}