{
    "Featured": [
        {
            "iID": "1f10f52933ea2d2970685eb49df3a2f3e45b43c7dfb968070074e2e12388b695534dd5281d19ad8278dbe0d655cbeeba6ef186d0796c108c4de4ed232ed81f2f",
            "iName": "Dominus",
            "iType": "Exotic Body",
            "iQuality": "Exotic",
            "iCategory": "Body",
            "iColor": "Gold",
            "iCertification": null,
            "iEdition": null,
            "iPrice": "1100",
            "iUpvote": "1834",
            "iDownvote": "429",
            "pulltimeCode": 1675195388494,
            "pulltimeText": "31-01-2023 21:03:08"
        },
        {
            "iID": "baa94b41834c1d5288734d4d69b4622d108b27a30fa747445c79cf5f232d3443b56e564d0437addcb916335a9c715a080dd57aa0f4d677466e140f9541a5a711",
            "iName": "Dueling Dragons",
            "iType": "Black Market Goal Explosion",
            "iQuality": "Black Market",
            "iCategory": "Goal explosion",
            "iColor": "Gold",
            "iCertification": null,
            "iEdition": null,
            "iPrice": "2500",
            "iUpvote": "375",
            "iDownvote": "34",
            "pulltimeCode": 1675195388495,
            "pulltimeText": "31-01-2023 21:03:08"
        }
    ],
    "Daily": [
        {
            "iID": "023dc068ca28aed96ae1e9f67aaa918c3e1362a79eca80fa50ae0b6c2a8ccd956d96167ab3afbfe4221497968db2ba94f6b970b1fe217cda8c4e35116a35593c",
            "iName": "Dominus: Pollo Caliente",
            "iType": "Rare Decal",
            "iQuality": "Rare",
            "iCategory": "Decal",
            "iColor": "",
            "iCertification": null,
            "iEdition": null,
            "iPrice": "50",
            "iUpvote": "17",
            "iDownvote": "123",
            "pulltimeCode": 1675195388498,
            "pulltimeText": "31-01-2023 21:03:08"
        },
        {
            "iID": "36beccc1c7acb732d052183c7ffe036e7cfab1f171d9ad3becd678c74ae7ebfd7b442eb9123f6953c24cd02215f2e5ef987c2e8a624206ed327ca2c76a91cec1",
            "iName": "Dominus: Funny Book",
            "iType": "Rare Decal",
            "iQuality": "Rare",
            "iCategory": "Decal",
            "iColor": "",
            "iCertification": null,
            "iEdition": null,
            "iPrice": "50",
            "iUpvote": "24",
            "iDownvote": "120",
            "pulltimeCode": 1675195388499,
            "pulltimeText": "31-01-2023 21:03:08"
        },
        {
            "iID": "d78102e5546d4dd3afc6278f730bc285e56c570399ab105d46c6501d13b16181f2b88aa44b584d2b6eee1fdc913b5e286efa1c1c2d23f4efb908b09dcc7d4709",
            "iName": "Incantor",
            "iType": "Very Rare Trail",
            "iQuality": "Very Rare",
            "iCategory": "Trail",
            "iColor": "Grey",
            "iCertification": null,
            "iEdition": null,
            "iPrice": "300",
            "iUpvote": "31",
            "iDownvote": "106",
            "pulltimeCode": 1675195388500,
            "pulltimeText": "31-01-2023 21:03:08"
        },
        {
            "iID": "236e8a5e0bc88e3c9f648f65de47d3ea515e30340a6890bc2fba2043ef17eb250564ca6526d4f34bcaa8b22ecafed514b75a892be92b0538822bf0bdcb8355b8",
            "iName": "Power-Shot",
            "iType": "Import Rocket Boost",
            "iQuality": "Import",
            "iCategory": "Rocket boost",
            "iColor": "Forest Green",
            "iCertification": null,
            "iEdition": null,
            "iPrice": "600",
            "iUpvote": "13",
            "iDownvote": "119",
            "pulltimeCode": 1675195388501,
            "pulltimeText": "31-01-2023 21:03:08"
        },
        {
            "iID": "99a6626437634a3e416251df731ab1cd53e68262116993ed7cdeb4c899b376766fcb61bf052f5ba06c3b1b456565dd9627e37284974eb599a21526f845db5d53",
            "iName": "Hasher",
            "iType": "Very Rare Wheels",
            "iQuality": "Very Rare",
            "iCategory": "Wheels",
            "iColor": "Cobalt",
            "iCertification": null,
            "iEdition": null,
            "iPrice": "500",
            "iUpvote": "9",
            "iDownvote": "117",
            "pulltimeCode": 1675195388502,
            "pulltimeText": "31-01-2023 21:03:08"
        },
        {
            "iID": "e73ad8fae0d3dbeba228a8c0bc23d061e29d8ed1ffb770aae96326f8e4bd16b841e3621aa5ea7347508ce59a441d0cd4a25b5a61945c90c8cdef89e12859c90a",
            "iName": "Dino",
            "iType": "Rare Paint",
            "iQuality": "Rare",
            "iCategory": "Paint",
            "iColor": "",
            "iCertification": null,
            "iEdition": null,
            "iPrice": "100",
            "iUpvote": "18",
            "iDownvote": "106",
            "pulltimeCode": 1675195388504,
            "pulltimeText": "31-01-2023 21:03:08"
        }
    ]
}