{
    "Featured_Items": [
        {
            "iID": "61293d5f6174aca9a9bd09411ec7e0fc",
            "iName": "Meteor Storm",
            "iType": "Black Market Goal Explosion",
            "iColor": "Pink",
            "iCertification": null,
            "iEdition": null,
            "iPrice": "2200",
            "iUpvote": "573",
            "iDownvote": "2085",
            "pulltimeCode": 1633105667882,
            "pulltimeText": "01-10-2021 18:27:47"
        },
        {
            "iID": "771c05e8aec0634eb6ca5f431c0785c4",
            "iName": "Pixel Fire",
            "iType": "Import Rocket Boost",
            "iColor": "Black",
            "iCertification": "Sweeper",
            "iEdition": null,
            "iPrice": "600",
            "iUpvote": "908",
            "iDownvote": "1772",
            "pulltimeCode": 1633105667884,
            "pulltimeText": "01-10-2021 18:27:47"
        }
    ],
    "DailyItems": [
        {
            "iID": "77034afd84d2f76f4cf226345ccbc684",
            "iName": "Gernot",
            "iType": "Exotic Wheels",
            "iColor": "",
            "iCertification": null,
            "iEdition": null,
            "iPrice": "700",
            "iUpvote": "208",
            "iDownvote": "2073",
            "pulltimeCode": 1633105667886,
            "pulltimeText": "01-10-2021 18:27:47"
        },
        {
            "iID": "54bea5b77a0b3512fe0b320f2c766a51",
            "iName": "Anthesis",
            "iType": "Very Rare Wheels",
            "iColor": "Saffron",
            "iCertification": null,
            "iEdition": null,
            "iPrice": "300",
            "iUpvote": "116",
            "iDownvote": "2075",
            "pulltimeCode": 1633105667887,
            "pulltimeText": "01-10-2021 18:27:47"
        },
        {
            "iID": "25453b723904a6a73719240b5d553ffb",
            "iName": "Circuit Board",
            "iType": "Rare Paint",
            "iColor": "",
            "iCertification": null,
            "iEdition": null,
            "iPrice": "100",
            "iUpvote": "211",
            "iDownvote": "1956",
            "pulltimeCode": 1633105667890,
            "pulltimeText": "01-10-2021 18:27:47"
        },
        {
            "iID": "cef87127c455123d7ab4894ee7892a02",
            "iName": "Merc: Athena",
            "iType": "Rare Decal",
            "iColor": "Burnt Sienna",
            "iCertification": "Juggler",
            "iEdition": null,
            "iPrice": "50",
            "iUpvote": "96",
            "iDownvote": "2066",
            "pulltimeCode": 1633105667891,
            "pulltimeText": "01-10-2021 18:27:47"
        },
        {
            "iID": "0104ae442fbf7f85e93c7d4eecefe96a",
            "iName": "Equalizer",
            "iType": "Exotic Wheels",
            "iColor": "",
            "iCertification": null,
            "iEdition": null,
            "iPrice": "800",
            "iUpvote": "344",
            "iDownvote": "1936",
            "pulltimeCode": 1633105667894,
            "pulltimeText": "01-10-2021 18:27:47"
        },
        {
            "iID": "9f5ac748900afb0bddd1d8912510b8d2",
            "iName": "Breakout: Shibuya",
            "iType": "Rare Decal",
            "iColor": "",
            "iCertification": null,
            "iEdition": null,
            "iPrice": "50",
            "iUpvote": "118",
            "iDownvote": "1993",
            "pulltimeCode": 1633105667895,
            "pulltimeText": "01-10-2021 18:27:47"
        }
    ]
}