{
    "Featured_Items": [
        {
            "iID": "c2dc77e6921cfb8171dddc8441eeb710",
            "iName": "Global: Encryption",
            "iType": "Black Market Decal",
            "iColor": "Purple",
            "iCertification": null,
            "iEdition": null,
            "iPrice": "2200",
            "iUpvote": "1410",
            "iDownvote": "2893",
            "pulltimeCode": 1631782952463,
            "pulltimeText": "16-09-2021 11:02:32"
        },
        {
            "iID": "23751808507ca432fc113cc580f9b321",
            "iName": "Glitch",
            "iType": "Import Wheels",
            "iColor": "Purple",
            "iCertification": null,
            "iEdition": "Glitched",
            "iPrice": "600",
            "iUpvote": "864",
            "iDownvote": "2982",
            "pulltimeCode": 1631782952465,
            "pulltimeText": "16-09-2021 11:02:32"
        }
    ],
    "DailyItems": [
        {
            "iID": "39b34d01259f922ecce791480ecaafab",
            "iName": "Apparatus",
            "iType": "Import Wheels",
            "iColor": "Pink",
            "iCertification": "Acrobat",
            "iEdition": null,
            "iPrice": "600",
            "iUpvote": "87",
            "iDownvote": "1657",
            "pulltimeCode": 1631782952473,
            "pulltimeText": "16-09-2021 11:02:32"
        },
        {
            "iID": "c14c2a888a883df220cc7bc2adede3a2",
            "iName": "Octane: Buzz Kill",
            "iType": "Rare Decal",
            "iColor": "Forest Green",
            "iCertification": null,
            "iEdition": null,
            "iPrice": "100",
            "iUpvote": "116",
            "iDownvote": "1597",
            "pulltimeCode": 1631782952475,
            "pulltimeText": "16-09-2021 11:02:32"
        },
        {
            "iID": "1f6ed252170e2a8489f2e646df95aa88",
            "iName": "Reactor",
            "iType": "Exotic Wheels",
            "iColor": "Saffron",
            "iCertification": null,
            "iEdition": null,
            "iPrice": "900",
            "iUpvote": "328",
            "iDownvote": "1442",
            "pulltimeCode": 1631782952477,
            "pulltimeText": "16-09-2021 11:02:32"
        },
        {
            "iID": "7e22dbf6a2c09763a538e85696df1a52",
            "iName": "Breakout: Taniwha",
            "iType": "Rare Decal",
            "iColor": "Forest Green",
            "iCertification": null,
            "iEdition": null,
            "iPrice": "100",
            "iUpvote": "49",
            "iDownvote": "1625",
            "pulltimeCode": 1631782952478,
            "pulltimeText": "16-09-2021 11:02:32"
        },
        {
            "iID": "16a7852dc1069fde7e347099a92bf2de",
            "iName": "Luminous",
            "iType": "Very Rare Trail",
            "iColor": "Cobalt",
            "iCertification": null,
            "iEdition": null,
            "iPrice": "400",
            "iUpvote": "444",
            "iDownvote": "1337",
            "pulltimeCode": 1631782952479,
            "pulltimeText": "16-09-2021 11:02:32"
        },
        {
            "iID": "b6fd6bc8141cba31ac2677c8549e93f1",
            "iName": "Pulse Crawler",
            "iType": "Very Rare Banner",
            "iColor": "Burnt Sienna",
            "iCertification": null,
            "iEdition": null,
            "iPrice": "200",
            "iUpvote": "91",
            "iDownvote": "1602",
            "pulltimeCode": 1631782952481,
            "pulltimeText": "16-09-2021 11:02:32"
        }
    ]
}